coloredterm/__init__.py
coloredterm/coloredterm.py
coloredterm-0.2.2.dist-info/LICENSE
coloredterm-0.2.2.dist-info/METADATA
coloredterm-0.2.2.dist-info/WHEEL
coloredterm-0.2.2.dist-info/top_level.txt
coloredterm-0.2.2.dist-info/RECORD
