Metadata-Version: 2.1
Name: coloredterm
Version: 0.2.2
Summary: Color the text in your terminal.
Home-page: https://github.com/hostedposted/coloredterm
Author: Hostedposted
Author-email: hostedpostedsite@gmail.com
License: UNKNOWN
Platform: UNKNOWN
Classifier: Programming Language :: Python :: 3.6
Classifier: Programming Language :: Python :: 3.7
Classifier: Programming Language :: Python :: 3.8
Classifier: Programming Language :: Python :: 3.9
Classifier: Operating System :: OS Independent
Classifier: License :: OSI Approved :: MIT License
Requires-Python: >=3.6
Requires-Dist: Pillow (<8.2.1)
